sintetic_library/__init__.py
sintetic_library/core.py
sintetic_client-0.1.0.dist-info/METADATA
sintetic_client-0.1.0.dist-info/WHEEL
sintetic_client-0.1.0.dist-info/top_level.txt
sintetic_client-0.1.0.dist-info/RECORD
