Metadata-Version: 2.4
Name: sintetic_client
Version: 0.1.0
Summary: Client Python per i servizi REST di Sintetic GeoDB
Author-email: Leandro Rocchi <leandro.rocchi@cnr.it>
Project-URL: Homepage, https://github.com/tuoutente/sintetic-client
Project-URL: Bug Tracker, https://github.com/tuoutente/sintetic-client/issues
Classifier: Programming Language :: Python :: 3
Classifier: License :: OSI Approved :: MIT License
Classifier: Operating System :: OS Independent
Classifier: Development Status :: 3 - Alpha
Requires-Python: >=3.6
Requires-Dist: requests>=2.25.0
Requires-Dist: pytz>=2021.1
Provides-Extra: dev
Requires-Dist: pytest>=6.0; extra == "dev"
Requires-Dist: pytest-cov>=2.0; extra == "dev"
Requires-Dist: black>=21.0; extra == "dev"
Requires-Dist: mypy>=0.900; extra == "dev"
